Metadata-Version: 2.4
Name: clinic-py
Version: 0.1.0
Summary: Non‑invasive performance metrics collection for Python
Author: fullzer4
Author-email: fullzer4 <gabrielpelizzaro@gmail.com>
License: MIT
Project-URL: Homepage, https://github.com/fullzer4/clinic-py
Project-URL: Repository, https://github.com/fullzer4/clinic-py
Project-URL: Issues, https://github.com/fullzer4/clinic-py/issues
Project-URL: Documentation, https://github.com/fullzer4/clinic-py#readme
Keywords: performance,monitoring,metrics,python,profiling,clinic
Classifier: Development Status :: 3 - Alpha
Classifier: Intended Audience :: Developers
Classifier: Programming Language :: Python :: 3
Classifier: Programming Language :: Python :: 3.9
Classifier: Programming Language :: Python :: 3.10
Classifier: Programming Language :: Python :: 3.11
Classifier: Programming Language :: Python :: 3.12
Classifier: Programming Language :: C
Classifier: Topic :: Software Development :: Libraries :: Python Modules
Classifier: Topic :: System :: Monitoring
Classifier: Topic :: Software Development :: Debuggers
Classifier: Operating System :: POSIX
Classifier: Operating System :: Unix
Requires-Python: >=3.9
License-File: LICENSE
Provides-Extra: dev
Requires-Dist: pytest>=7.0; extra == "dev"
Requires-Dist: black>=23.0; extra == "dev"
Requires-Dist: flake8>=6.0; extra == "dev"
Requires-Dist: mypy>=1.0; extra == "dev"
Requires-Dist: build>=0.10.0; extra == "dev"
Requires-Dist: twine>=4.0.0; extra == "dev"
Dynamic: author
Dynamic: license-file
